tu/__init__.py
tu-0.0.5.dist-info/licenses/LICENSE
tu-0.0.5.dist-info/METADATA
tu-0.0.5.dist-info/WHEEL
tu-0.0.5.dist-info/top_level.txt
tu-0.0.5.dist-info/RECORD
